simple_imshow-1.0.post1.dist-info/DESCRIPTION.rst
simple_imshow-1.0.post1.dist-info/LICENSE.txt
simple_imshow-1.0.post1.dist-info/METADATA
simple_imshow-1.0.post1.dist-info/RECORD
simple_imshow-1.0.post1.dist-info/WHEEL
simple_imshow-1.0.post1.dist-info/metadata.json
simple_imshow-1.0.post1.dist-info/top_level.txt
simshow/__init__.py
simshow/simshow.py
