Metadata-Version: 2.0
Name: simple-imshow
Version: 1.0.post1
Summary: A simple tool to display (and read to np.ndarray) images from a url, file, image object, etc.
Home-page: https://github.com/mathandy/simple-imshow
Author: Andy Port
Author-email: AndyAPort@gmail.com
License: MIT
Download-URL: http://github.com/mathandy/simple-imshow/tarball/1.0.post1
Keywords: image,images,display,read,imshow,imread
Platform: OS Independent
Classifier: Development Status :: 4 - Beta
Classifier: Intended Audience :: Developers
Classifier: License :: OSI Approved :: MIT License
Classifier: Operating System :: OS Independent
Classifier: Programming Language :: Python :: 2
Classifier: Programming Language :: Python :: 3
Classifier: Topic :: Multimedia :: Graphics
Classifier: Topic :: Scientific/Engineering :: Image Recognition
Classifier: Topic :: Scientific/Engineering :: Information Analysis
Classifier: Topic :: Scientific/Engineering :: Visualization
Classifier: Topic :: Software Development :: Libraries :: Python Modules
Requires: numpy
Requires: scipy
Requires: matplotlib
Requires: requests
